project_done/.DS_Store
project_done/__init__.py
project_done/done.py
project_done/sound_effects/mixkit-retro-game-notification-212.wav
project_done-0.1.4.dist-info/WHEEL
project_done-0.1.4.dist-info/METADATA
project_done-0.1.4.dist-info/RECORD
