Metadata-Version: 2.1
Name: project-done
Version: 0.1.4
Summary: 
Requires-Python: >=3.8,<4.0
Classifier: Programming Language :: Python :: 3
Classifier: Programming Language :: Python :: 3.10
Classifier: Programming Language :: Python :: 3.8
Classifier: Programming Language :: Python :: 3.9
Requires-Dist: ipython (>=8.1.1,<9.0.0)
